{
  "title": "325 - L'ascens del nazisme",
  "description": "Les reparacions de guerra imposades a Alemanya pel Tractat de Versalles a la fi de la Primera Guerra Mundial van sumir el país en una dura depressió política i econòmica. En aquest context de crisi i desencant de les classes mitjanes, apareixia el 1920 el Partit Nacionalista dels Treballadors Alemanys liderat per l'excaporal austríac Adolf Hitler. El periodista Jordi Finestres recorda el procés que va portar al poder el nacionalsocialisme el 1933, després del seu pas per les urnes.",
  "duration": "00:57:14",
  "date": "12/09/2010 15:00:00",
  "link": "https://www.3cat.cat/3cat/en-guardia/audio/465930/",
  "audio_url": "https://img.3cat.cat/multimedia/mp3/4/4/1284365722144.mp3",
  "image": "https://img.3cat.cat/multimedia/https://img.3cat.cat/multimedia/jpg/8/7/1284024916878.jpg",
  "filename": "325-l-ascens-del-nazisme.mp3"
}