{
  "title": "371 - La indústria làctia catalana",
  "description": "A partir del 1880, el desenvolupament dels processos d'higienització va fer que el consum de llet es deixés de considerar una pràctica de risc i es generalitzés a les ciutats. Van ser els inicis d'una potent indústria catalana amb productes com Cacaolat o empreses pioneres com Letona, fundada per l'avi de Jordi Viader, periodista, doctor en Història i autor de la tesi \"Cent anys d'indústria làctia a Catalunya (1879 ¿ 1979)\".",
  "duration": "00:52:52",
  "date": "19/06/2011 15:00:00",
  "link": "https://www.3cat.cat/3cat/en-guardia/audio/543096/",
  "audio_url": "https://img.3cat.cat/multimedia/mp3/7/6/1308505050167.mp3",
  "image": "https://img.3cat.cat/multimedia/jpg/0/1/1308223093910.jpg",
  "filename": "371-la-indústria-làctia-catalana.mp3",
  "image_filename": "371-la-indústria-làctia-catalana.jpg"
}