{
  "title": "484 - La lluita antifranquista dels 70 (resistència 1)",
  "description": "Dues manifestacions històriques a Barcelona el febrer del 1976 i un primer Onze de Setembre fora de la clandestinitat celebrat a Sant Boi de Llobregat. Aquests van ser els esdeveniments amb què culminava la feina de l'Assemblea de Catalunya, l'organisme clandestí unitari creat per forces socials i polítiques catalanes en els últims anys del franquisme. L'historiador Carles Santacana enceta la sèrie sobre la resistència antifranquista recordant els precedents de la celebració de la Diada durant els anys 70 del segle XX.",
  "duration": "00:53:35",
  "date": "11/09/2013 22:00:00",
  "link": "https://www.3cat.cat/3cat/en-guardia/audio/754215/",
  "audio_url": "https://img.3cat.cat/multimedia/mp3/7/2/1378934421027.mp3",
  "image": "https://img.3cat.cat/multimedia/jpg/4/5/1693573786454.jpg",
  "filename": "484-la-lluita-antifranquista-dels-70-resistència-1.mp3",
  "image_filename": "484-la-lluita-antifranquista-dels-70-resistència-1.jpg"
}