{
  "title": "510 - Carme Ballester (dones 3)",
  "description": "Militant d'Estat Català i compromesa políticament des de ben jove, la vida de la segona esposa de Lluís Companys va estar profundament lligada a la causa de Catalunya i al record del president assassinat. Oriol Dueñas, tècnic del Memorial Democràtic de la Generalitat, repassa la biografia i la trajectòria política de la dona que va acompanyar Companys en l'exili i que, després de 29 anys de l'execució del seu marit, va recordar els fets en un manuscrit adreçat al govern alemany en demanda d'una pensió com a víctima del nazisme.",
  "duration": "00:52:30",
  "date": "02/02/2014 15:00:00",
  "link": "https://www.3cat.cat/3cat/en-guardia/audio/788041/",
  "audio_url": "https://img.3cat.cat/multimedia/mp3/8/7/1391360760178.mp3",
  "image": "https://img.3cat.cat/multimedia/jpg/4/5/1693573786454.jpg",
  "filename": "510-carme-ballester-dones-3.mp3",
  "image_filename": "510-carme-ballester-dones-3.jpg"
}