{
  "title": "657 - Guerra Freda 4. La crisi dels míssils",
  "description": "L'octubre de 1962, el govern nord-americà va rebre la prova fotogràfica que els soviètics preparaven míssils amb prou abast per arribar al seu territori des de les bases aèries cubanes. S'obria la crisi dels míssils, tretze dies que van tensionar el món i que, tot i tenir com a protagonistes els governs cubà, nord-americà i rus, es va acabar resolent gairebé en secret als despatxos de Kennedy i Khrusxov. En el quart capítol dedicat a la Guerra Freda, Enric Calpena conversa amb el periodista i historiador Pep Martí i Vallverdú sobre aquest episodi i el pacte que hi va posar fi, l'acord que va perpetuar el líder cubà Fidel Castro al poder.",
  "duration": "00:55:41",
  "date": "19/03/2017 16:00:00",
  "link": "https://www.3cat.cat/3cat/en-guardia/audio/954168/",
  "audio_url": "https://img.3cat.cat/multimedia/mp3/9/0/1489051507109.mp3",
  "image": "https://img.3cat.cat/multimedia/https://img.3cat.cat/multimedia/jpg/7/8/1489506482987.jpg",
  "filename": "657-guerra-freda-4.-la-crisi-dels-míssils.mp3"
}