{
  "title": "658 - El retorn de Tarradellas",
  "description": "El 23 d'octubre del 1977, el president de la Generalitat a l'exili, Josep Tarradellas, tornava a Catalunya, després de setmanes de tenses i complexes negociacions amb el govern presidit per Adolfo Suárez. L'historiador Enric Pujol, autor de \"Josep Tarradellas. El retorn del president, juny-desembre 1977\", rememora els detalls d'aquesta delicada operació, que suposava el reconeixement institucional de la Generalitat per part de l'estat espanyol i és recordada, entre altres motius, per l'històric \"Ja sóc aquí\" del president.",
  "duration": "00:54:33",
  "date": "26/03/2017 16:00:00",
  "link": "https://www.3cat.cat/3cat/en-guardia/audio/956093/",
  "audio_url": "https://img.3cat.cat/multimedia/mp3/7/0/1490263827807.mp3",
  "image": "https://img.3cat.cat/multimedia/https://img.3cat.cat/multimedia/jpg/3/0/1490269943803.jpg",
  "filename": "658-el-retorn-de-tarradellas.mp3"
}