{
  "title": "El monestir de Santa Maria d'Alguaire",
  "description": "Capítol 951. El monestir femení hospitaler més important de la Catalunya medieval i moderna va ser Santa Maria d'Alguaire, construït a mitjans del segle XIII i abandonat a finals del segle XVII. Des d'una ubicació privilegiada, va exercir un control econòmic, social i jurisdiccional sobre diversos enclavaments de la plana del Segrià. Tot i que el règim de la comunitat era d'aïllament, s'han conservat documents que demostren que les normes de clausura van ser vulnerades repetidament, fins que va arribar una priora, a finals del segle XVI, decidida a posar ordre. En parlem amb Josep M. Solé i Sabaté, historiador, i Maria Soler, doctora en Història per la Universitat de Barcelona, coordinadora del Doble Grau d'Arqueologia i Història i vicedegana de la Facultat de Geografia i Història de la UB.",
  "duration": "00:52:22",
  "date": "18/09/2022 15:00:00",
  "link": "https://www.3cat.cat/3cat/en-guardia/audio/1146100/",
  "audio_url": "https://img.3cat.cat/multimedia/mp3/6/3/1663170059636.mp3",
  "image": "https://img.3cat.cat/multimedia/https://img.3cat.cat/multimedia/jpg/3/6/1663170060763.jpg",
  "filename": "el-monestir-de-santa-maria-d-alguaire.mp3"
}