{
  "title": "Karl Marx",
  "description": "Capítol 720. Les idees que va formular sobre la lluita de classes i la necessitat que la classe obrera participés activament en el funcionament dels governs van conformar l'ideari polític i social d'una part molt important del món el segle passat. Era un intel·lectual i a la vegada un home d'acció. No es va considerar mai a si mateix ni filòsof, ni economista, ni polític... sinó un crític de la filosofia, l'economia i la política. Era Karl Marx. En parlem amb Josep M. Solé i Sabaté, historiador, i Ramon Alcoberro, llicenciat en Filosofia i Ciències de l'Educació a la UB, que manté una pàgina web i un bloc sobre temes filosòfics.",
  "duration": "00:55:25",
  "date": "23/12/2018 15:05:00",
  "link": "https://www.3cat.cat/3cat/en-guardia/audio/1024435/",
  "audio_url": "https://img.3cat.cat/multimedia/mp3/1/3/1545318020331.mp3",
  "image": "https://img.3cat.cat/multimedia/jpg/5/4/1545318021545.jpg",
  "filename": "karl-marx.mp3",
  "image_filename": "karl-marx.jpg"
}