{
  "title": "Les galeres",
  "description": "Capítol 777. Ja des del segle XIII, la principal empresa catalana era el comerç a la Mediterrània. El control de la mar era clau per fer aquesta activitat, però també per defensar-se en cas d'atac, per tant calia disposar de bons vaixells de guerra i, des de l'època antiga fins a la moderna, aquest vaixell era la galera. Conscients de la importància de mantenir una bona flota, a Barcelona es van aixecar unes drassanes militars que no tenien res a envejar a les d'altres ciutats europees. En parlem amb Josep M. Solé i Sabaté, historiador, i amb Enric Garcia, cap de documentació del Museu Marítim de Barcelona.",
  "duration": "00:54:06",
  "date": "04/10/2020 15:00:00",
  "link": "https://www.3cat.cat/3cat/en-guardia/audio/1080557/",
  "audio_url": "https://img.3cat.cat/multimedia/mp3/6/2/1601894125126.mp3",
  "image": "https://img.3cat.cat/multimedia/jpg/6/3/1601894125836.jpg",
  "filename": "les-galeres.mp3",
  "image_filename": "les-galeres.jpg"
}