{
  "title": "Luter i la seva influència",
  "description": "Capítol 848. La irrupció de la impremta a l'Europa del segle XV va revolucionar tots els àmbits del coneixement humà, també en la vessant més religiosa i espiritual. Fa més de cinc-cents anys, Martí Luter es va valer de la impremta, el gran invent de la seva època, per fer arribar els textos bíblics i les seves propostes de reforma d'un cristianisme més enfocat a la pràctica que a la mística. La revolució tecnològica va fer possible la revolució teològica, una reforma que de ser religiosa va passar a ser també política, econòmica i cultural. Aquestes idees van donar origen al protestantisme, i des d'Alemanya es van estendre pel centre i el nord d'Europa. En parlem amb Josep M. Solé i Sabaté, historiador, i Antoni Gelonch, acadèmic d'honor de la Reial Acadèmia de Belles Arts de Sant Jordi, autor de \"Luter i la seva influència. Buscant la veritat, va canviar la història\" i també \"Napoleó, la revolució i els catalans\".",
  "duration": "00:55:02",
  "date": "12/06/2021 15:00:00",
  "link": "https://www.3cat.cat/3cat/en-guardia/audio/1104023/",
  "audio_url": "https://img.3cat.cat/multimedia/mp3/8/6/1623240928468.mp3",
  "image": "https://img.3cat.cat/multimedia/https://img.3cat.cat/multimedia/jpg/3/2/1623240931123.jpg",
  "filename": "luter-i-la-seva-influència.mp3"
}