{
  "title": "Poema de Gilgamesh",
  "description": "Capítol 1048. La primera fita de la literatura universal i el gran llegat de les civilitzacions sumèria i babilònica que narra les aventures d'un personatge, el rei d'Uruk, una antiga ciutat de Mesopotàmia. Sembla que Gilgamesh va existir històricament, tot i que només se'n conserva una narració èpica que exalça les seves virtuts i aborda alguns dels grans temes que han preocupat des de sempre l'ésser humà, com l'amistat, el poder i l'anhel d'immortalitat. Es tracta d'uns textos d'escriptura cuneïforme, gravats en tauletes de fang, els més antics dels quals són del segon mil·lenni abans de Crist, i per tant tenen uns quatre mil anys d'antiguitat. En parlem amb Josep Maria Solé i Sabaté, historiador, i Adelina Millet, doctora per la Sorbona, secretària acadèmica de l'Institut del Pròxim Orient Antic i professora del Departament de Filologia Clàssica, Romànica i Semítica de la UB; juntament amb Lluís Feliu, traductor del \"Poema de Gilgamesh\" al català, en l'edició d'Adesiara.",
  "duration": "00:54:57",
  "date": "28/10/2023 06:00:00",
  "link": "https://www.3cat.cat/3cat/en-guardia/audio/1186396/",
  "audio_url": "https://img.3cat.cat/multimedia/mp3/2/0/1698162360102.mp3",
  "image": "https://img.3cat.cat/multimedia/png/6/1/1698427241316.png",
  "filename": "poema-de-gilgamesh.mp3",
  "image_filename": "poema-de-gilgamesh.png"
}